ORD/__init__.py
ORD/ord_cash.py
ORD/ord_core.py
ORD/ord_fn.py
ORD/ord_receipt.py
ORD/ord_setting.py
ORD/ord_shift.py
ORD/test/ORD_test.py
ORD/test/__init__.py
ord-1.8.25.1.dist-info/METADATA
ord-1.8.25.1.dist-info/WHEEL
ord-1.8.25.1.dist-info/top_level.txt
ord-1.8.25.1.dist-info/RECORD
