Metadata-Version: 2.4
Name: ORD
Version: 1.8.25.1
Summary: Module for working with the ATOL cash register driver
Home-page: https://github.com/brandshopru
Author: Vladimir Smirnov
Author-email: volodya@brandshop.ru
Dynamic: author
Dynamic: author-email
Dynamic: description
Dynamic: description-content-type
Dynamic: home-page
Dynamic: summary
